setup.py
distributions_cbf/Binomialdistribution.py
distributions_cbf/Gaussiandistribution.py
distributions_cbf/Generaldistribution.py
distributions_cbf/__init__.py
distributions_cbf.egg-info/PKG-INFO
distributions_cbf.egg-info/SOURCES.txt
distributions_cbf.egg-info/dependency_links.txt
distributions_cbf.egg-info/not-zip-safe
distributions_cbf.egg-info/top_level.txt