Metadata-Version: 1.0
Name: distributions-cbf
Version: 0.1
Summary: Gaussian distributions
Home-page: UNKNOWN
Author: Cesar Blanco
Author-email: cblanco@learning.eoi.es
License: UNKNOWN
Platform: UNKNOWN
